<?xml version="1.0" encoding="UTF-8"?>
<list>
  <sentences>
    <s path="file:/D:/Corpora/oanc/data/written_1/journal/slate/49/ArticleIP_19030.anc" start="1479" end="1484" sStart="-1" offset="0" sid="null" wn="1" wnkey="try%2:41:00::" text="Among the recurring themes: his belief in the primacy of the individual over the group (&quot;[My work] &lt;b&gt;tries&lt;/b&gt; to reveal the extent to which each of us is responsible for his own fate&quot;) and his intense, conflicted Americanism (&quot;I am too vindictively American, too full of hate for the hateful aspects of this country, and too possessed by the things I love here to be too long away&quot;)." />
    <s path="file:/c:/OANC/data/written_1/journal/slate/49/ArticleIP_19030.anc" start="3163" end="3167" sStart="null" offset="0" sid="null" wn="1" wnkey="time%1:11:00::" text="Punishment of children, the article recounts, &quot;should be unpleasant, memorable, and inflicted at a &lt;b&gt;time&lt;/b&gt; that is convenient for the parent.&quot;" />
    <s path="file:/c:/OANC/data/written_1/journal/slate/49/ArticleIP_19030.anc" start="3163" end="3167" sStart="null" offset="0" sid="null" wn="3" wnkey="time%1:28:00::" text="Punishment of children, the article recounts, &quot;should be unpleasant, memorable, and inflicted at a &lt;b&gt;time&lt;/b&gt; that is convenient for the parent.&quot;" />
    <s path="[OANC]/data/written_1/journal/slate/49/ArticleIP_19030.anc" start="7975" end="7979" sStart="null" offset="58" sid="r9.kill.v.0631" wn="1" wnkey="kill%2:35:00::" text="A writer examines suicide notes to investigate why people kill themselves." />
    <s path="file:/D:/Corpora/oanc/data/written_1/journal/slate/49/ArticleIP_19030.anc" start="5856" end="5865" sStart="null" offset="0" sid="null" wn="1" wnkey="justify%2:32:00::" text="A self-identified member of the &quot;black elite&quot; &lt;b&gt;justifies&lt;/b&gt; the group's snobbery and separatism." />
    <s path="file:/D:/Corpora/oanc/data/written_1/journal/slate/49/ArticleIP_19030.anc" start="5856" end="5865" sStart="null" offset="0" sid="null" wn="1" wnkey="justify%2:32:00::" text="A self-identified member of the &quot;black elite&quot; &lt;b&gt;justifies&lt;/b&gt; the group's snobbery and separatism." />
    <s path="[OANC]/data/written_1/journal/slate/49/ArticleIP_19030.anc" start="8361" end="8365" sStart="null" offset="62" sid="r10.high.j.0650" wn="1" wnkey="high%3:00:02::" text="The magazine explains why the president's poll numbers are so high: 1) he courts them (&quot;like a kid who gets straight A's by flattering the teacher&quot;); and 2) polling questions are phrased with a calculation and nuance that are positively, well, Clintonesque." />
  </sentences>
</list>