<?xml version="1.0" encoding="UTF-8"?>
<list>
  <sentences>
    <s path="[OANC]/data/written_2/technical/plos/journal.pbio.0020052.anc" start="3806" end="3810" sStart="3785" offset="21" sid="r11.true.j.0821" wn="1" wnkey="true%3:00:00::" text="If this were true, it would make sense to tolerate all sorts of bad outcomes, because the fruits of R&amp;D eventually benefit everyone." />
    <s path="[OANC]/data/written_2/technical/plos/journal.pbio.0020052.anc" start="9605" end="9615" sStart="null" offset="105" sid="r1.successful.j.0029" wn="1" wnkey="successful%3:00:00::" text="Prize systems could be designed to be fairly similar to the current system, with big payoffs for successful entrepreneurs, but even with this approach, there would be huge opportunities to improve welfare." />
    <s path="[OANC]/data/written_2/technical/plos/journal.pbio.0020052.anc" start="9605" end="9615" sStart="null" offset="105" sid="r1.successful.j.0029" wn="1" wnkey="successful%3:00:00::" text="Prize systems could be designed to be fairly similar to the current system, with big payoffs for successful entrepreneurs, but even with this approach, there would be huge opportunities to improve welfare." />
    <s path="[OANC]/data/written_2/technical/plos/journal.pbio.0020052.anc" start="9605" end="9615" sStart="null" offset="105" sid="r1.successful.j.0029" wn="1" wnkey="successful%3:00:00::" text="Prize systems could be designed to be fairly similar to the current system, with big payoffs for successful entrepreneurs, but even with this approach, there would be huge opportunities to improve welfare." />
    <s path="[OANC]/data/written_2/technical/plos/journal.pbio.0020052.anc" start="7265" end="7271" sStart="null" offset="77" sid="r11.severe.j.0627" wn="5" wnkey="severe%5:00:00:critical:03" text="The NIH already has a track record in developing important drugs for severe illnesses, such as cancer or AIDS, showing that this is a viable model." />
    <s path="[OANC]/data/written_2/technical/plos/journal.pbio.0020052.anc" start="8616" end="8624" sStart="null" offset="132" sid="r11.refer.v.0416" wn="7" wnkey="refer%2:32:04::" text="An alternative market-based approach is one in which R&amp;D organisations compete for rewards for specific R&amp;D output, referred to by economists as a prize model (Wright 1983; Kremer 1998; Shavell and van Ypersele 2001)." />
    <s path="file:/D:/Corpora/oanc/data/written_2/technical/plos/journal.pbio.0020052.anc" start="9239" end="9244" sStart="null" offset="0" sid="null" wn="1" wnkey="rapid%5:00:00:fast:01" text="If products were protected by patents or other intellectual property claims, the government could grant compulsory licenses (a procedure allowed by trade agreements to override monopoly rights on a patent, in return for compensation to rights owners; see Box 1) and permit &lt;b&gt;rapid&lt;/b&gt; introduction of generic competition." />
    <s path="file:/D:/Corpora/oanc/data/written_2/technical/plos/journal.pbio.0020052.anc" start="9239" end="9244" sStart="null" offset="0" sid="null" wn="1" wnkey="rapid%5:00:00:fast:01" text="If products were protected by patents or other intellectual property claims, the government could grant compulsory licenses (a procedure allowed by trade agreements to override monopoly rights on a patent, in return for compensation to rights owners; see Box 1) and permit &lt;b&gt;rapid&lt;/b&gt; introduction of generic competition." />
    <s path="[OANC]/data/written_2/technical/plos/journal.pbio.0020052.anc" start="13604" end="13608" sStart="null" offset="175" sid="r7.poor.j.0973" wn="2147483645" wnkey="null" text="We can raise global R&amp;D levels as a matter of policy and ensure that resources flow into the areas of the greatest need, and we can do so knowing that the poor and the rich will have access to new inventions at marginal cost." />
    <s path="[OANC]/data/written_2/technical/plos/journal.pbio.0020052.anc" start="13604" end="13608" sStart="null" offset="175" sid="r7.poor.j.0973" wn="2147483645" wnkey="null" text="We can raise global R&amp;D levels as a matter of policy and ensure that resources flow into the areas of the greatest need, and we can do so knowing that the poor and the rich will have access to new inventions at marginal cost." />
    <s path="[OANC]/data/written_2/technical/plos/journal.pbio.0020052.anc" start="12632" end="12642" sStart="null" offset="117" sid="r10.particular.j.0402" wn="2" wnkey="particular%5:00:02:specific:00" text="Government would set the required contribution, but the individual (or employer) would be free to choose the particular intermediator that received their contributions." />
    <s path="[OANC]/data/written_2/technical/plos/journal.pbio.0020052.anc" start="14376" end="14386" sStart="null" offset="127" sid="r1.influence.n.0027" wn="1" wnkey="influence%1:07:00::" text="At the same time, the system of prescribing medicines will be transformed by a substantial reduction in the distorting influences of the current multibillion-dollar industry of marketing medicines to doctors and (increasingly) directly to the public." />
    <s path="[OANC]/data/written_2/technical/plos/journal.pbio.0020052.anc" start="14376" end="14386" sStart="null" offset="127" sid="r1.influence.n.0027" wn="4" wnkey="influence%1:19:00::" text="At the same time, the system of prescribing medicines will be transformed by a substantial reduction in the distorting influences of the current multibillion-dollar industry of marketing medicines to doctors and (increasingly) directly to the public." />
    <s path="[OANC]/data/written_2/technical/plos/journal.pbio.0020052.anc" start="14376" end="14386" sStart="null" offset="127" sid="r1.influence.n.0027" wn="4" wnkey="influence%1:19:00::" text="At the same time, the system of prescribing medicines will be transformed by a substantial reduction in the distorting influences of the current multibillion-dollar industry of marketing medicines to doctors and (increasingly) directly to the public." />
  </sentences>
</list>