<?xml version="1.0" encoding="UTF-8"?>
<list>
  <sentences>
    <s path="[OANC]/data/written_1/journal/slate/15/Article247_3802.anc" start="1654" end="1658" sStart="1451" offset="203" sid="r8.live.v.0892" wn="1" wnkey="live%2:42:08::" annotator="cgozo" text="As she went on and on about $12,000 bottles of 1870 wine (actually, I'd kind of like to try one) and a Park Avenue apartment building where the grungy units start at $4 million (why anyone would want to live on a street where your furniture shifts whenever the commuter trains rumble beneath is beyond me), she cleverly pointed out the analogies with the '80s economic bubble and the dot-com one ..." />
    <s path="file:/c:/OANC/data/written_1/journal/slate/15/Article247_3802.anc" start="920" end="924" sStart="null" offset="0" sid="null" wn="9" wnkey="land%1:14:00::" annotator="rstandig" text=". On the other is Al Gore, notable for (as you put it about JFK Jr.) not living up to his Fair Deal hero father's high standards of integrity and cojones . How can these two turkeys be our leading candidates for the highest office in the &lt;b&gt;land&lt;/b&gt;?" />
    <s path="file:/c:/OANC/data/written_1/journal/slate/15/Article247_3802.anc" start="1060" end="1064" sStart="null" offset="0" sid="null" wn="3" wnkey="land%1:15:01::" annotator="rstandig" text="The answer, methinks, is that the presidency attracts losers because it's not even in the top 500 highest offices of the &lt;b&gt;land&lt;/b&gt;." />
    <s path="file:/c:/OANC/data/written_1/journal/slate/15/Article247_3802.anc" start="920" end="924" sStart="null" offset="0" sid="null" wn="3" wnkey="land%1:15:01::" annotator="elstickles" text=". On the other is Al Gore, notable for (as you put it about JFK Jr.) not living up to his Fair Deal hero father's high standards of integrity and cojones . How can these two turkeys be our leading candidates for the highest office in the &lt;b&gt;land&lt;/b&gt;?" />
    <s path="file:/c:/OANC/data/written_1/journal/slate/15/Article247_3802.anc" start="920" end="924" sStart="null" offset="0" sid="null" wn="3" wnkey="land%1:15:01::" annotator="comcgeetubb" text=". On the other is Al Gore, notable for (as you put it about JFK Jr.) not living up to his Fair Deal hero father's high standards of integrity and cojones . How can these two turkeys be our leading candidates for the highest office in the &lt;b&gt;land&lt;/b&gt;?" />
    <s path="file:/c:/OANC/data/written_1/journal/slate/15/Article247_3802.anc" start="920" end="924" sStart="null" offset="0" sid="null" wn="9" wnkey="land%1:14:00::" annotator="cgozo" text=". On the other is Al Gore, notable for (as you put it about JFK Jr.) not living up to his Fair Deal hero father's high standards of integrity and cojones . How can these two turkeys be our leading candidates for the highest office in the &lt;b&gt;land&lt;/b&gt;?" />
    <s path="file:/c:/OANC/data/written_1/journal/slate/15/Article247_3802.anc" start="920" end="924" sStart="null" offset="0" sid="null" wn="3" wnkey="land%1:15:01::" annotator="carichter" text=". On the other is Al Gore, notable for (as you put it about JFK Jr.) not living up to his Fair Deal hero father's high standards of integrity and cojones . How can these two turkeys be our leading candidates for the highest office in the &lt;b&gt;land&lt;/b&gt;?" />
    <s path="file:/c:/OANC/data/written_1/journal/slate/15/Article247_3802.anc" start="920" end="924" sStart="null" offset="0" sid="null" wn="3" wnkey="land%1:15:01::" annotator="brubin" text=". On the other is Al Gore, notable for (as you put it about JFK Jr.) not living up to his Fair Deal hero father's high standards of integrity and cojones . How can these two turkeys be our leading candidates for the highest office in the &lt;b&gt;land&lt;/b&gt;?" />
    <s path="file:/c:/OANC/data/written_1/journal/slate/15/Article247_3802.anc" start="920" end="924" sStart="null" offset="0" sid="null" wn="5" wnkey="land%1:15:02::" annotator="brubin" text=". On the other is Al Gore, notable for (as you put it about JFK Jr.) not living up to his Fair Deal hero father's high standards of integrity and cojones . How can these two turkeys be our leading candidates for the highest office in the &lt;b&gt;land&lt;/b&gt;?" />
  </sentences>
</list>