<?xml version="1.0" encoding="UTF-8"?>
<list>
  <sentences>
    <s path="file:/D:/Corpora/oanc/data/written_1/journal/slate/6/Article247_700.anc" start="253" end="257" sStart="-1" offset="0" sid="null" wn="2" wnkey="rate%1:21:00::" annotator="veweser" text="The Los Angeles Times and USA Today lead with Fed Chairman Alan Greenspan's suggestion in congressional testimony Wednesday that he foresees a cut next week in the fed funds &lt;b&gt;rate&lt;/b&gt;, which determines the cost of money throughout the economy." />
    <s path="file:/D:/Corpora/oanc/data/written_1/journal/slate/6/Article247_700.anc" start="253" end="257" sStart="null" offset="0" sid="null" wn="2" wnkey="rate%1:21:00::" annotator="jeneale" text="The Los Angeles Times and USA Today lead with Fed Chairman Alan Greenspan's suggestion in congressional testimony Wednesday that he foresees a cut next week in the fed funds &lt;b&gt;rate&lt;/b&gt;, which determines the cost of money throughout the economy." />
    <s path="file:/D:/Corpora/oanc/data/written_1/journal/slate/6/Article247_700.anc" start="253" end="257" sStart="null" offset="0" sid="null" wn="2" wnkey="rate%1:21:00::" annotator="cgozo" text="The Los Angeles Times and USA Today lead with Fed Chairman Alan Greenspan's suggestion in congressional testimony Wednesday that he foresees a cut next week in the fed funds &lt;b&gt;rate&lt;/b&gt;, which determines the cost of money throughout the economy." />
    <s path="file:/D:/Corpora/oanc/data/written_1/journal/slate/6/Article247_700.anc" start="253" end="257" sStart="null" offset="0" sid="null" wn="2" wnkey="rate%1:21:00::" annotator="brubin" text="The Los Angeles Times and USA Today lead with Fed Chairman Alan Greenspan's suggestion in congressional testimony Wednesday that he foresees a cut next week in the fed funds &lt;b&gt;rate&lt;/b&gt;, which determines the cost of money throughout the economy." />
    <s path="file:/D:/Corpora/oanc/data/written_1/journal/slate/6/Article247_700.anc" start="1291" end="1297" sStart="null" offset="0" sid="null" wn="8" wnkey="world_power%1:14:00::" annotator="carichter" text="The story does go on to point out some hopeful developments in the relationship between the two rival A-&lt;b&gt;powers&lt;/b&gt;: at meetings in New York yesterday, their prime ministers agreed to resume high-level talks about the region in dispute between them, Kashmir, and also to set-up a communications &quot;hot line.&quot;" />
    <s path="file:/D:/Corpora/oanc/data/written_1/journal/slate/6/Article247_700.anc" start="2204" end="2211" sStart="null" offset="0" sid="null" wn="5" wnkey="chance%1:26:01::" annotator="veweser" text="By the way, USAT says a survey it took among 49 top economists rates the &lt;b&gt;chances&lt;/b&gt; of a U.S. recession next year as one in four." />
    <s path="file:/D:/Corpora/oanc/data/written_1/journal/slate/6/Article247_700.anc" start="2204" end="2211" sStart="null" offset="0" sid="null" wn="4" wnkey="chance%1:07:00::" annotator="veweser" text="By the way, USAT says a survey it took among 49 top economists rates the &lt;b&gt;chances&lt;/b&gt; of a U.S. recession next year as one in four." />
    <s path="file:/D:/Corpora/oanc/data/written_1/journal/slate/6/Article247_700.anc" start="2204" end="2211" sStart="null" offset="0" sid="null" wn="4" wnkey="chance%1:07:00::" annotator="rstandig" text="By the way, USAT says a survey it took among 49 top economists rates the &lt;b&gt;chances&lt;/b&gt; of a U.S. recession next year as one in four." />
    <s path="file:/D:/Corpora/oanc/data/written_1/journal/slate/6/Article247_700.anc" start="2204" end="2211" sStart="null" offset="0" sid="null" wn="4" wnkey="chance%1:07:00::" annotator="elstickles" text="By the way, USAT says a survey it took among 49 top economists rates the &lt;b&gt;chances&lt;/b&gt; of a U.S. recession next year as one in four." />
    <s path="file:/D:/Corpora/oanc/data/written_1/journal/slate/6/Article247_700.anc" start="2204" end="2211" sStart="null" offset="0" sid="null" wn="4" wnkey="chance%1:07:00::" annotator="comcgeetubb" text="By the way, USAT says a survey it took among 49 top economists rates the &lt;b&gt;chances&lt;/b&gt; of a U.S. recession next year as one in four." />
    <s path="file:/D:/Corpora/oanc/data/written_1/journal/slate/6/Article247_700.anc" start="2204" end="2211" sStart="null" offset="0" sid="null" wn="" wnkey="null" annotator="chisom" text="By the way, USAT says a survey it took among 49 top economists rates the &lt;b&gt;chances&lt;/b&gt; of a U.S. recession next year as one in four." />
    <s path="file:/D:/Corpora/oanc/data/written_1/journal/slate/6/Article247_700.anc" start="2204" end="2211" sStart="null" offset="0" sid="null" wn="4" wnkey="chance%1:07:00::" annotator="carichter" text="By the way, USAT says a survey it took among 49 top economists rates the &lt;b&gt;chances&lt;/b&gt; of a U.S. recession next year as one in four." />
    <s path="file:/D:/Corpora/oanc/data/written_1/journal/slate/6/Article247_700.anc" start="2204" end="2211" sStart="null" offset="0" sid="null" wn="4" wnkey="chance%1:07:00::" annotator="carichter" text="By the way, USAT says a survey it took among 49 top economists rates the &lt;b&gt;chances&lt;/b&gt; of a U.S. recession next year as one in four." />
    <s path="[OANC]/data/written_1/journal/slate/6/Article247_700.anc" start="2023" end="2029" sStart="null" offset="46" sid="r9.appear.v.0191" wn="4" wnkey="appear%2:39:01::" annotator="cgozo" text="The LAT points out however, that there do not appear to be any similar coordinated cuts forthcoming from the central banks of Europe's leading economies." />
  </sentences>
</list>