<?xml version="1.0" encoding="UTF-8"?>
<list>
  <sentences>
    <s path="file:/D:/Corpora/oanc/data/spoken/telephone/switchboard/27/sw2792-ms98-a-trans.anc" start="1296" end="1303" sStart="-1" offset="0" sid="null" wn="2" wnkey="write%2:32:00::" annotator="tofox" text="you know things that are &lt;b&gt;written&lt;/b&gt; by like Christian authors or um" />
    <s path="file:/D:/Corpora/oanc/data/spoken/telephone/switchboard/27/sw2792-ms98-a-trans.anc" start="5461" end="5468" sStart="null" offset="0" sid="null" wn="2" wnkey="success%1:04:00::" annotator="veweser" text="i i like to uh read about people who've been a successful you know who've who made a &lt;b&gt;success&lt;/b&gt; of their lives" />
    <s path="file:/D:/Corpora/oanc/data/spoken/telephone/switchboard/27/sw2792-ms98-a-trans.anc" start="5461" end="5468" sStart="null" offset="0" sid="null" wn="3" wnkey="success%1:26:00::" annotator="cgozo" text="i i like to uh read about people who've been a successful you know who've who made a &lt;b&gt;success&lt;/b&gt; of their lives" />
    <s path="file:/D:/Corpora/oanc/data/spoken/telephone/switchboard/27/sw2792-ms98-a-trans.anc" start="5461" end="5468" sStart="null" offset="0" sid="null" wn="2" wnkey="success%1:04:00::" annotator="brubin" text="i i like to uh read about people who've been a successful you know who've who made a &lt;b&gt;success&lt;/b&gt; of their lives" />
    <s path="file:/D:/Corpora/oanc/data/spoken/telephone/switchboard/27/sw2792-ms98-a-trans.anc" start="1462" end="1466" sStart="null" offset="0" sid="null" wn="1" wnkey="read%2:31:00::" annotator="veweser" text="doctors about family and you know how to improve your home and all that kind of thing um i like to &lt;b&gt;read&lt;/b&gt; the magazines i to &lt;b&gt;read&lt;/b&gt; like i like to &lt;b&gt;read&lt;/b&gt; Readers' Digest i &lt;b&gt;read&lt;/b&gt; a lot of bicycling magazines" />
    <s path="file:/D:/Corpora/oanc/data/spoken/telephone/switchboard/27/sw2792-ms98-a-trans.anc" start="1462" end="1466" sStart="null" offset="0" sid="null" wn="1" wnkey="read%2:31:00::" annotator="veweser" text="doctors about family and you know how to improve your home and all that kind of thing um i like to &lt;b&gt;read&lt;/b&gt; the magazines i to &lt;b&gt;read&lt;/b&gt; like i like to &lt;b&gt;read&lt;/b&gt; Readers' Digest i &lt;b&gt;read&lt;/b&gt; a lot of bicycling magazines" />
    <s path="file:/D:/Corpora/oanc/data/spoken/telephone/switchboard/27/sw2792-ms98-a-trans.anc" start="1462" end="1466" sStart="null" offset="0" sid="null" wn="1" wnkey="read%2:31:00::" annotator="jeneale" text="doctors about family and you know how to improve your home and all that kind of thing um i like to &lt;b&gt;read&lt;/b&gt; the magazines i to &lt;b&gt;read&lt;/b&gt; like i like to &lt;b&gt;read&lt;/b&gt; Readers' Digest i &lt;b&gt;read&lt;/b&gt; a lot of bicycling magazines" />
    <s path="file:/D:/Corpora/oanc/data/spoken/telephone/switchboard/27/sw2792-ms98-a-trans.anc" start="7415" end="7419" sStart="null" offset="0" sid="null" wn="1" wnkey="read%2:31:00::" annotator="cgozo" text="there may be some schools you could &lt;b&gt;read&lt;/b&gt; about and learn" />
    <s path="file:/D:/Corpora/oanc/data/spoken/telephone/switchboard/27/sw2792-ms98-a-trans.anc" start="10835" end="10839" sStart="null" offset="0" sid="null" wn="1" wnkey="read%2:31:00::" annotator="brubin" text="it's pretty sad a lot of people that work for me that can't even spell or &lt;b&gt;read&lt;/b&gt; you know" />
    <s path="file:/D:/Corpora/oanc/data/spoken/telephone/switchboard/27/sw2792-ms98-a-trans.anc" start="1462" end="1466" sStart="null" offset="0" sid="null" wn="1" wnkey="read%2:31:00::" annotator="brubin" text="doctors about family and you know how to improve your home and all that kind of thing um i like to &lt;b&gt;read&lt;/b&gt; the magazines i to &lt;b&gt;read&lt;/b&gt; like i like to &lt;b&gt;read&lt;/b&gt; Readers' Digest i &lt;b&gt;read&lt;/b&gt; a lot of bicycling magazines" />
    <s path="file:/D:/Corpora/oanc/data/spoken/telephone/switchboard/27/sw2792-ms98-a-trans.anc" start="2683" end="2687" sStart="null" offset="0" sid="null" wn="1" wnkey="read%2:31:00::" annotator="brubin" text="like about eleven more books than i would have &lt;b&gt;read&lt;/b&gt; last year but so far i've only &lt;b&gt;read&lt;/b&gt; like two books and so i'm not doing very well but" />
    <s path="file:/D:/Corpora/oanc/data/spoken/telephone/switchboard/27/sw2792-ms98-a-trans.anc" start="1462" end="1466" sStart="null" offset="0" sid="null" wn="1" wnkey="read%2:31:00::" annotator="a4" text="doctors about family and you know how to improve your home and all that kind of thing um i like to &lt;b&gt;read&lt;/b&gt; the magazines i to &lt;b&gt;read&lt;/b&gt; like i like to &lt;b&gt;read&lt;/b&gt; Readers' Digest i &lt;b&gt;read&lt;/b&gt; a lot of bicycling magazines" />
    <s path="file:/D:/Corpora/oanc/data/spoken/telephone/switchboard/27/sw2792-ms98-a-trans.anc" start="1462" end="1466" sStart="null" offset="0" sid="null" wn="1" wnkey="read%2:31:00::" annotator="a3" text="doctors about family and you know how to improve your home and all that kind of thing um i like to &lt;b&gt;read&lt;/b&gt; the magazines i to &lt;b&gt;read&lt;/b&gt; like i like to &lt;b&gt;read&lt;/b&gt; Readers' Digest i &lt;b&gt;read&lt;/b&gt; a lot of bicycling magazines" />
    <s path="file:/D:/Corpora/oanc/data/spoken/telephone/switchboard/27/sw2792-ms98-a-trans.anc" start="1462" end="1466" sStart="null" offset="0" sid="null" wn="1" wnkey="read%2:31:00::" annotator="a2" text="doctors about family and you know how to improve your home and all that kind of thing um i like to &lt;b&gt;read&lt;/b&gt; the magazines i to &lt;b&gt;read&lt;/b&gt; like i like to &lt;b&gt;read&lt;/b&gt; Readers' Digest i &lt;b&gt;read&lt;/b&gt; a lot of bicycling magazines" />
    <s path="file:/D:/Corpora/oanc/data/spoken/telephone/switchboard/27/sw2792-ms98-a-trans.anc" start="1462" end="1466" sStart="null" offset="0" sid="null" wn="1" wnkey="read%2:31:00::" annotator="a1" text="doctors about family and you know how to improve your home and all that kind of thing um i like to &lt;b&gt;read&lt;/b&gt; the magazines i to &lt;b&gt;read&lt;/b&gt; like i like to &lt;b&gt;read&lt;/b&gt; Readers' Digest i &lt;b&gt;read&lt;/b&gt; a lot of bicycling magazines" />
  </sentences>
</list>