<?xml version="1.0" encoding="UTF-8"?>
<list>
  <sentences>
    <s path="[OANC]/data/written_1/journal/slate/15/Article247_3838.anc" start="3702" end="3708" sStart="3638" offset="64" sid="r7.sight.n.0024" wn="4" wnkey="sight%1:09:03::" text="A front-page LAT news analysis is less rosy because it sets its sights on long-term prospects for Pakistani democracy, rather than on allaying immediate international worries." />
    <s path="[OANC]/data/written_1/journal/slate/15/Article247_3838.anc" start="3702" end="3708" sStart="null" offset="64" sid="r7.sight.n.0024" wn="2147483646" wnkey="null" text="A front-page LAT news analysis is less rosy because it sets its sights on long-term prospects for Pakistani democracy, rather than on allaying immediate international worries." />
    <s path="[OANC]/data/written_1/journal/slate/15/Article247_3838.anc" start="3702" end="3708" sStart="null" offset="64" sid="r7.sight.n.0024" wn="4" wnkey="sight%1:09:03::" text="A front-page LAT news analysis is less rosy because it sets its sights on long-term prospects for Pakistani democracy, rather than on allaying immediate international worries." />
    <s path="[OANC]/data/written_1/journal/slate/15/Article247_3838.anc" start="3702" end="3708" sStart="null" offset="64" sid="r7.sight.n.0024" wn="2147483647" wnkey="null" text="A front-page LAT news analysis is less rosy because it sets its sights on long-term prospects for Pakistani democracy, rather than on allaying immediate international worries." />
    <s path="[OANC]/data/written_1/journal/slate/15/Article247_3838.anc" start="1783" end="1789" sStart="null" offset="137" sid="r9.kill.v.0794" wn="9" wnkey="kill%2:35:02::" text="The Hector Mine earthquake, named for a mineral mine near the epicenter, was three times more powerful than the 6.7-magnitude quake that killed 57 people in L.A. in 1994." />
    <s path="[OANC]/data/written_1/journal/slate/15/Article247_3838.anc" start="1123" end="1127" sStart="null" offset="26" sid="r10.help.v.0876" wn="1" wnkey="help%2:41:00::" text="Clinton is now itching to help Russia finish a missile-tracking radar in Siberia." />
    <s path="[OANC]/data/written_1/journal/slate/15/Article247_3838.anc" start="5391" end="5396" sStart="null" offset="172" sid="r8.ask.v.0335" wn="4" wnkey="ask%2:32:04::" text="The piece, which also looks at former President George Bush's life in letters, discusses the Texas governor's executive qualities: &quot;When the National Journal recently asked him how he made decisions, he replied, 'I'm a decisive person." />
  </sentences>
</list>