<?xml version="1.0" encoding="UTF-8"?>
<list>
  <sentences>
    <s path="[OANC]/data/written_1/journal/slate/45/ArticleIP_3567.anc" start="2734" end="2741" sStart="2723" offset="11" sid="r8.suggest.v.0044" wn="1" wnkey="suggest%2:32:00::" text="How do you suggest I approach the topic?" />
    <s path="[OANC]/data/written_1/journal/slate/45/ArticleIP_3567.anc" start="2734" end="2741" sStart="null" offset="11" sid="r8.suggest.v.0044" wn="1" wnkey="suggest%2:32:00::" text="How do you suggest I approach the topic?" />
    <s path="[OANC]/data/written_1/journal/slate/45/ArticleIP_3567.anc" start="2734" end="2741" sStart="null" offset="11" sid="r8.suggest.v.0044" wn="1" wnkey="suggest%2:32:00::" text="How do you suggest I approach the topic?" />
    <s path="[OANC]/data/written_1/journal/slate/45/ArticleIP_3567.anc" start="2734" end="2741" sStart="null" offset="11" sid="r8.suggest.v.0044" wn="1" wnkey="suggest%2:32:00::" text="How do you suggest I approach the topic?" />
    <s path="[OANC]/data/written_1/journal/slate/45/ArticleIP_3567.anc" start="7568" end="7578" sStart="null" offset="73" sid="r11.recommend.v.0210" wn="1" wnkey="recommend%2:32:01::" text="Prudie understands that you guys are between a rock and a hard drive but recommends that you sign off with as little rancor as you can manage." />
    <s path="file:/D:/Corpora/oanc/data/written_1/journal/slate/45/ArticleIP_3567.anc" start="6272" end="6276" sStart="null" offset="0" sid="null" wn="2" wnkey="meet%2:41:01::" text="Now he wants to &lt;b&gt;meet&lt;/b&gt; her for coffee, &quot;just to have a chat.&quot;" />
    <s path="file:/D:/Corpora/oanc/data/written_1/journal/slate/45/ArticleIP_3567.anc" start="5587" end="5590" sStart="null" offset="0" sid="null" wn="6" wnkey="meet%2:41:03::" text="When he left the hospital (he was treated for depression and a sleep disorder) he got an e-mail address for a woman he &lt;b&gt;met&lt;/b&gt; there." />
    <s path="[OANC]/data/written_1/journal/slate/45/ArticleIP_3567.anc" start="6030" end="6035" sStart="null" offset="101" sid="null" wn="7" wnkey="level%1:09:00::" text="I should tell you that a few years ago he had an impotence problem and couldn't manage on a physical level, so I got into cybersex." />
    <s path="[OANC]/data/written_1/journal/slate/45/ArticleIP_3567.anc" start="6030" end="6035" sStart="null" offset="101" sid="null" wn="3" wnkey="level%1:26:00::" text="I should tell you that a few years ago he had an impotence problem and couldn't manage on a physical level, so I got into cybersex." />
    <s path="[OANC]/data/written_1/journal/slate/45/ArticleIP_3567.anc" start="6030" end="6035" sStart="null" offset="101" sid="null" wn="3" wnkey="level%1:26:00::" text="I should tell you that a few years ago he had an impotence problem and couldn't manage on a physical level, so I got into cybersex." />
    <s path="[OANC]/data/written_1/journal/slate/45/ArticleIP_3567.anc" start="6030" end="6035" sStart="null" offset="101" sid="null" wn="1" wnkey="level%1:07:00::" text="I should tell you that a few years ago he had an impotence problem and couldn't manage on a physical level, so I got into cybersex." />
    <s path="[OANC]/data/written_1/journal/slate/45/ArticleIP_3567.anc" start="6030" end="6035" sStart="null" offset="101" sid="null" wn="" wnkey="null" text="I should tell you that a few years ago he had an impotence problem and couldn't manage on a physical level, so I got into cybersex." />
    <s path="[OANC]/data/written_1/journal/slate/45/ArticleIP_3567.anc" start="6030" end="6035" sStart="null" offset="101" sid="null" wn="3" wnkey="level%1:26:00::" text="I should tell you that a few years ago he had an impotence problem and couldn't manage on a physical level, so I got into cybersex." />
  </sentences>
</list>