<?xml version="1.0" encoding="UTF-8"?>
<list>
  <sentences>
    <s path="file:/D:/Corpora/oanc/data/spoken/face-to-face/charlotte/HodgesSamuel.anc" start="5513" end="5519" sStart="-1" offset="0" sid="null" wn="1" wnkey="try%2:41:00::" text="He's got his arm and uh he's &lt;b&gt;trying&lt;/b&gt; to put it on his body and it didn't fit and it's too short and it didn't look like his arm so he throws it aside and goes on." />
    <s path="file:/D:/Corpora/oanc/data/spoken/face-to-face/charlotte/HodgesSamuel.anc" start="5513" end="5519" sStart="null" offset="0" sid="null" wn="1" wnkey="try%2:41:00::" text="He's got his arm and uh he's &lt;b&gt;trying&lt;/b&gt; to put it on his body and it didn't fit and it's too short and it didn't look like his arm so he throws it aside and goes on." />
    <s path="file:/D:/Corpora/oanc/data/spoken/face-to-face/charlotte/HodgesSamuel.anc" start="5513" end="5519" sStart="null" offset="0" sid="null" wn="1" wnkey="try%2:41:00::" text="He's got his arm and uh he's &lt;b&gt;trying&lt;/b&gt; to put it on his body and it didn't fit and it's too short and it didn't look like his arm so he throws it aside and goes on." />
    <s path="file:/D:/Corpora/oanc/data/spoken/face-to-face/charlotte/HodgesSamuel.anc" start="5513" end="5519" sStart="null" offset="0" sid="null" wn="1" wnkey="try%2:41:00::" text="He's got his arm and uh he's &lt;b&gt;trying&lt;/b&gt; to put it on his body and it didn't fit and it's too short and it didn't look like his arm so he throws it aside and goes on." />
    <s path="file:/D:/Corpora/oanc/data/spoken/face-to-face/charlotte/HodgesSamuel.anc" start="5513" end="5519" sStart="null" offset="0" sid="null" wn="1" wnkey="try%2:41:00::" text="He's got his arm and uh he's &lt;b&gt;trying&lt;/b&gt; to put it on his body and it didn't fit and it's too short and it didn't look like his arm so he throws it aside and goes on." />
    <s path="file:/D:/Corpora/oanc/data/spoken/face-to-face/charlotte/HodgesSamuel.anc" start="4275" end="4281" sStart="null" offset="0" sid="null" wn="1" wnkey="rip%2:35:00::" text="Finally the mountain lion &lt;b&gt;ripped&lt;/b&gt; off his arm his left arm." />
    <s path="file:/D:/Corpora/oanc/data/spoken/face-to-face/charlotte/HodgesSamuel.anc" start="4275" end="4281" sStart="null" offset="0" sid="null" wn="1" wnkey="rip%2:35:00::" text="Finally the mountain lion &lt;b&gt;ripped&lt;/b&gt; off his arm his left arm." />
    <s path="file:/D:/Corpora/oanc/data/spoken/face-to-face/charlotte/HodgesSamuel.anc" start="4275" end="4281" sStart="null" offset="0" sid="null" wn="2147483647" wnkey="null" text="Finally the mountain lion &lt;b&gt;ripped&lt;/b&gt; off his arm his left arm." />
    <s path="file:/D:/Corpora/oanc/data/spoken/face-to-face/charlotte/HodgesSamuel.anc" start="4275" end="4281" sStart="null" offset="0" sid="null" wn="2147483647" wnkey="null" text="Finally the mountain lion &lt;b&gt;ripped&lt;/b&gt; off his arm his left arm." />
    <s path="file:/D:/Corpora/oanc/data/spoken/face-to-face/charlotte/HodgesSamuel.anc" start="4275" end="4281" sStart="null" offset="0" sid="null" wn="1" wnkey="rip%2:35:00::" text="Finally the mountain lion &lt;b&gt;ripped&lt;/b&gt; off his arm his left arm." />
    <s path="file:/D:/Corpora/oanc/data/spoken/face-to-face/charlotte/HodgesSamuel.anc" start="4275" end="4281" sStart="null" offset="0" sid="null" wn="1" wnkey="rip%2:35:00::" text="Finally the mountain lion &lt;b&gt;ripped&lt;/b&gt; off his arm his left arm." />
    <s path="file:/D:/Corpora/oanc/data/spoken/face-to-face/charlotte/HodgesSamuel.anc" start="4275" end="4281" sStart="null" offset="0" sid="null" wn="1" wnkey="rip%2:35:00::" text="Finally the mountain lion &lt;b&gt;ripped&lt;/b&gt; off his arm his left arm." />
    <s path="file:/D:/Corpora/oanc/data/spoken/face-to-face/charlotte/HodgesSamuel.anc" start="4275" end="4281" sStart="null" offset="0" sid="null" wn="1" wnkey="rip%2:35:00::" text="Finally the mountain lion &lt;b&gt;ripped&lt;/b&gt; off his arm his left arm." />
    <s path="file:/D:/Corpora/oanc/data/spoken/face-to-face/charlotte/HodgesSamuel.anc" start="4275" end="4281" sStart="null" offset="0" sid="null" wn="1" wnkey="rip%2:35:00::" text="Finally the mountain lion &lt;b&gt;ripped&lt;/b&gt; off his arm his left arm." />
    <s path="file:/D:/Corpora/oanc/data/spoken/face-to-face/charlotte/HodgesSamuel.anc" start="4275" end="4281" sStart="null" offset="0" sid="null" wn="1" wnkey="rip%2:35:00::" text="Finally the mountain lion &lt;b&gt;ripped&lt;/b&gt; off his arm his left arm." />
    <s path="file:/D:/Corpora/oanc/data/spoken/face-to-face/charlotte/HodgesSamuel.anc" start="4275" end="4281" sStart="null" offset="0" sid="null" wn="2147483647" wnkey="null" text="Finally the mountain lion &lt;b&gt;ripped&lt;/b&gt; off his arm his left arm." />
    <s path="file:/D:/Corpora/oanc/data/spoken/face-to-face/charlotte/HodgesSamuel.anc" start="4275" end="4281" sStart="null" offset="0" sid="null" wn="1" wnkey="rip%2:35:00::" text="Finally the mountain lion &lt;b&gt;ripped&lt;/b&gt; off his arm his left arm." />
    <s path="file:/D:/Corpora/oanc/data/spoken/face-to-face/charlotte/HodgesSamuel.anc" start="4275" end="4281" sStart="null" offset="0" sid="null" wn="1" wnkey="rip%2:35:00::" text="Finally the mountain lion &lt;b&gt;ripped&lt;/b&gt; off his arm his left arm." />
    <s path="file:/D:/Corpora/oanc/data/spoken/face-to-face/charlotte/HodgesSamuel.anc" start="4524" end="4531" sStart="null" offset="0" sid="null" wn="2" wnkey="become%2:42:01::" text="So he doesn't know but he, he doesn't die he survives um and grows old &lt;b&gt;becomes&lt;/b&gt; an old, old, an old Indian and, um, um, &lt;b&gt;becomes&lt;/b&gt; you know one of the leaders of the tribe but he's always got this one goal is to find that mountain lion that got his arm and really he doesn't really care that much about the mountain lion he wants his arm or somebody's arm." />
    <s path="file:/D:/Corpora/oanc/data/spoken/face-to-face/charlotte/HodgesSamuel.anc" start="4476" end="4483" sStart="null" offset="0" sid="null" wn="2" wnkey="become%2:42:01::" text="So he doesn't know but he, he doesn't die he survives um and grows old &lt;b&gt;becomes&lt;/b&gt; an old, old, an old Indian and, um, um, &lt;b&gt;becomes&lt;/b&gt; you know one of the leaders of the tribe but he's always got this one goal is to find that mountain lion that got his arm and really he doesn't really care that much about the mountain lion he wants his arm or somebody's arm." />
  </sentences>
</list>